serving/__init__.py
serving/app.py
serving/auth.py
serving/cli.py
serving/config.py
serving/csrf_middleware.py
serving/error_handler.py
serving/events.py
serving/exception_handlers.py
serving/exception_middleware.py
serving/forms.py
serving/injectors.py
serving/response.py
serving/router.py
serving/serv.py
serving/serv_middleware.py
serving/session.py
serving/types.py
serving/utilities.py
serving/templates/error.html
getserving-0.1.1a10.dist-info/METADATA
getserving-0.1.1a10.dist-info/WHEEL
getserving-0.1.1a10.dist-info/entry_points.txt
getserving-0.1.1a10.dist-info/licenses/LICENSE
getserving-0.1.1a10.dist-info/RECORD
