Metadata-Version: 2.4
Name: getserving
Version: 0.1.1a10
Summary: A powerful, dependency-injection-driven ASGI web framework for Python with first-class support for configuration management, type-safe routing, and extensible middleware.
Project-URL: Homepage, https://github.com/ZechCodes/Serving
Project-URL: Documentation, https://github.com/ZechCodes/Serving/tree/main/docs
Project-URL: Repository, https://github.com/ZechCodes/Serving
Project-URL: Issues, https://github.com/ZechCodes/Serving/issues
Project-URL: Changelog, https://github.com/ZechCodes/Serving/blob/main/CHANGELOG.md
Author-email: Zechariah Zimmerman <zzimmerman@8ly.com>
Maintainer-email: Zechariah Zimmerman <zzimmerman@8ly.com>
License: MIT License
License-File: LICENSE
Keywords: api,asgi,framework,http,web
Classifier: Development Status :: 3 - Alpha
Classifier: Framework :: AsyncIO
Classifier: Intended Audience :: Developers
Classifier: License :: OSI Approved :: MIT License
Classifier: Programming Language :: Python :: 3
Classifier: Programming Language :: Python :: 3.13
Classifier: Topic :: Internet :: WWW/HTTP :: HTTP Servers
Classifier: Topic :: Internet :: WWW/HTTP :: WSGI :: Application
Classifier: Topic :: Software Development :: Libraries :: Python Modules
Requires-Python: >=3.13
Requires-Dist: bevy>=3.1.0b9
Requires-Dist: jinja2>=3.1.6
Requires-Dist: python-multipart>=0.0.20
Requires-Dist: pyyaml>=6.0.2
Requires-Dist: starlette>=0.41.0
Requires-Dist: websockets>=15.0.1
Requires-Dist: werkzeug>=3.1.3
Provides-Extra: server
Requires-Dist: uvicorn>=0.34.2; extra == 'server'
